ai_tools/__init__.py
ai_tools/core.py
lchpersonal_ai_tools-0.1.5.dist-info/licenses/LICENSE
lchpersonal_ai_tools-0.1.5.dist-info/METADATA
lchpersonal_ai_tools-0.1.5.dist-info/WHEEL
lchpersonal_ai_tools-0.1.5.dist-info/top_level.txt
lchpersonal_ai_tools-0.1.5.dist-info/RECORD
