Metadata-Version: 2.4
Name: lchpersonal-ai-tools
Version: 0.1.5
Summary: 简单实用的AI工具包
Home-page: https://github.com/lchpersonal/ai-tools
Author: lchpersonal
Author-email: lchpersonal <326018662@qq.com>
License-Expression: MIT
Project-URL: Homepage, https://github.com/lchpersonal/ai-tools
Project-URL: Bug Reports, https://github.com/lchpersonal/ai-tools/issues
Project-URL: Source, https://github.com/lchpersonal/ai-tools
Keywords: ai,tools,utilities
Classifier: Development Status :: 3 - Alpha
Classifier: Intended Audience :: Developers
Classifier: Operating System :: OS Independent
Classifier: Programming Language :: Python :: 3
Classifier: Programming Language :: Python :: 3.7
Classifier: Programming Language :: Python :: 3.8
Classifier: Programming Language :: Python :: 3.9
Classifier: Programming Language :: Python :: 3.10
Classifier: Programming Language :: Python :: 3.11
Requires-Python: >=3.7
License-File: LICENSE
Dynamic: author
Dynamic: home-page
Dynamic: license-file
Dynamic: requires-python
